cps_learnai_mcp_demo/__init__.py
cps_learnai_mcp_demo-0.1.6.dist-info/METADATA
cps_learnai_mcp_demo-0.1.6.dist-info/WHEEL
cps_learnai_mcp_demo-0.1.6.dist-info/entry_points.txt
cps_learnai_mcp_demo-0.1.6.dist-info/RECORD
