Metadata-Version: 2.4
Name: cps-learnai-mcp-demo
Version: 0.1.6
Summary: Add your description here
Author-email: 叽哩呱啦 <3425658642@qq.com>
Requires-Python: >=3.8
Requires-Dist: mcp[cli]>=1.11.0
